{
    "os": "Linux-4.15.0-213-generic-x86_64-with-glibc2.10",
    "python": "3.8.5",
    "heartbeatAt": "2024-05-14T12:54:23.304827",
    "startedAt": "2024-05-14T12:54:21.724802",
    "docker": null,
    "cuda": "10.2.89",
    "args": [
        "-ll",
        "3",
        "-r",
        "3",
        "-bs",
        "128",
        "-pn",
        "optgamma",
        "-Mts",
        "60",
        "90",
        "120",
        "150",
        "180",
        "210",
        "240",
        "-e",
        "100",
        "-Mss",
        "360",
        "480",
        "-dcms",
        "1",
        "-Ns",
        "6000",
        "-Nt",
        "6000",
        "-gms",
        "0.05",
        "0.1",
        "0.3",
        "0.5",
        "0.7",
        "0.9",
        "0.95"
    ],
    "state": "running",
    "program": "main.py",
    "codePathLocal": "main.py",
    "codePath": "main.py",
    "git": {
        "remote": "https://github.com/huseyin-karaca/DANN_py3.git",
        "commit": "0b3b4ae276e396efa2dfe5fe6706fc3334469e06"
    },
    "email": "huseyinkaraccca@gmail.com",
    "root": "/home/huseyin/fungtion/dannpy_yeniden/DANN_py3",
    "host": "elif",
    "username": "huseyin",
    "executable": "/home/huseyin/anaconda3/envs/dannpy5/bin/python",
    "cpu_count": 4,
    "cpu_count_logical": 8,
    "cpu_freq": {
        "current": 2579.665375,
        "min": 800.0,
        "max": 4100.0
    },
    "cpu_freq_per_core": [
        {
            "current": 2404.969,
            "min": 800.0,
            "max": 4100.0
        },
        {
            "current": 2678.726,
            "min": 800.0,
            "max": 4100.0
        },
        {
            "current": 2405.606,
            "min": 800.0,
            "max": 4100.0
        },
        {
            "current": 2760.13,
            "min": 800.0,
            "max": 4100.0
        },
        {
            "current": 2994.976,
            "min": 800.0,
            "max": 4100.0
        },
        {
            "current": 2627.756,
            "min": 800.0,
            "max": 4100.0
        },
        {
            "current": 2161.125,
            "min": 800.0,
            "max": 4100.0
        },
        {
            "current": 2604.035,
            "min": 800.0,
            "max": 4100.0
        }
    ],
    "disk": {
        "/": {
            "total": 467.8886032104492,
            "used": 279.4864501953125
        }
    },
    "gpu": "Quadro P600",
    "gpu_count": 1,
    "gpu_devices": [
        {
            "name": "Quadro P600",
            "memory_total": 2097479680
        }
    ],
    "memory": {
        "total": 15.558303833007812
    }
}
